README.rst
setup.py
zagoload/__init__.py
zagoload/cachemode.py
zagoload/fileloader.py
zagoload/filerequest.py
zagoload/ftpinfo.py
zagoload/helpers.py
zagoload/requeststate.py
zagoload.egg-info/PKG-INFO
zagoload.egg-info/SOURCES.txt
zagoload.egg-info/dependency_links.txt
zagoload.egg-info/requires.txt
zagoload.egg-info/top_level.txt