Metadata-Version: 1.1
Name: zagoload
Version: 0.5.1
Summary: Download files(http,ftp). Supports: cache, uniform access to remote and local files
Home-page: https://github.com/napuzba/zagoload.git
Author: napuzba
Author-email: kobi@napuzba.com
License: MIT
Keywords: download,crawl,ftp,http,json,webservices,cache
Platform: UNKNOWN
Classifier: Topic :: Software Development :: Libraries :: Python Modules
Classifier: Topic :: Internet :: File Transfer Protocol (FTP)
Classifier: Topic :: Internet :: WWW/HTTP :: Indexing/Search
Classifier: Development Status :: 3 - Alpha
Classifier: License :: OSI Approved :: MIT License
Classifier: Programming Language :: Python :: 2
Classifier: Programming Language :: Python :: 3
Classifier: Operating System :: OS Independent
Classifier: Intended Audience :: Developers
Classifier: Intended Audience :: Information Technology
Classifier: Intended Audience :: Science/Research
Classifier: Intended Audience :: System Administrators
